CHANGES
LICENSE
MANIFEST.in
README
README.md
osdf.py
request.py
setup.cfg
setup.py
bin/osdf
osdf_python.egg-info/PKG-INFO
osdf_python.egg-info/SOURCES.txt
osdf_python.egg-info/dependency_links.txt
osdf_python.egg-info/requires.txt
osdf_python.egg-info/top_level.txt
test/__init__.py
test/test.py
test/test_osdf.py