Metadata-Version: 1.0
Name: osdf-python
Version: 0.7
Summary: Python client to Open Science Data Framework (OSDF) REST servers.
Home-page: http://osdf.igs.umaryland.edu
Author: Victor Felix
Author-email: victor73@github.com
License: MIT
Platform: UNKNOWN
Classifier: Development Status :: 5 - Production/Stable
Classifier: License :: OSI Approved :: MIT License
Classifier: Intended Audience :: Science/Research
Classifier: Natural Language :: English
Classifier: Operating System :: POSIX
Classifier: Programming Language :: Python :: 2.7
Classifier: Topic :: Utilities
Classifier: Topic :: Scientific/Engineering
Classifier: Topic :: Scientific/Engineering :: Bio-Informatics
